crewai_playground/__init__.py
crewai_playground/cli.py
crewai_playground/server.py
crewai_playground/events/__init__.py
crewai_playground/events/event_listener.py
crewai_playground/events/events.py
crewai_playground/events/websocket_utils.py
crewai_playground/handlers/__init__.py
crewai_playground/handlers/chat_handler.py
crewai_playground/loaders/__init__.py
crewai_playground/loaders/crew_loader.py
crewai_playground/loaders/flow_loader.py
crewai_playground/loaders/tool_loader.py
crewai_playground/routers/__init__.py
crewai_playground/routers/evaluation_api.py
crewai_playground/routers/flow_api.py
crewai_playground/services/__init__.py
crewai_playground/services/entities.py
crewai_playground/services/telemetry.py
crewai_playground/ui/build/client/favicon.ico
crewai_playground/ui/build/client/index.html
crewai_playground/ui/build/client/assets/FlowNavigation-DHrQLs8L.js
crewai_playground/ui/build/client/assets/KickoffNavigation-DfJcBmsR.js
crewai_playground/ui/build/client/assets/Layout-CP5Hc7nX.js
crewai_playground/ui/build/client/assets/alert-DAr1l6eU.js
crewai_playground/ui/build/client/assets/badge-CzGG4LGd.js
crewai_playground/ui/build/client/assets/card-DMpzrDC2.js
crewai_playground/ui/build/client/assets/chat-B5ayM3-e.js
crewai_playground/ui/build/client/assets/chat-CpKl2eGN.css
crewai_playground/ui/build/client/assets/chevron-down-BlJJcPQY.js
crewai_playground/ui/build/client/assets/chunk-GNGMS2XR-KLeu_BA0.js
crewai_playground/ui/build/client/assets/circle-alert-CVY5oy2y.js
crewai_playground/ui/build/client/assets/clock-D9RgnNZI.js
crewai_playground/ui/build/client/assets/crews-D4k-wRAs.js
crewai_playground/ui/build/client/assets/crews.evals-DY4A8dLt.js
crewai_playground/ui/build/client/assets/crews.traces-B5LGikU6.js
crewai_playground/ui/build/client/assets/dashboard-OrXBNP0D.js
crewai_playground/ui/build/client/assets/entry.client-k3jdAZ5Z.js
crewai_playground/ui/build/client/assets/flows-CK6FLUYa.css
crewai_playground-0.1.0a13.dist-info/METADATA
crewai_playground-0.1.0a13.dist-info/WHEEL
crewai_playground-0.1.0a13.dist-info/entry_points.txt
crewai_playground-0.1.0a13.dist-info/top_level.txt
crewai_playground-0.1.0a13.dist-info/RECORD
