Metadata-Version: 2.4
Name: crewai-playground
Version: 0.1.0a13
Summary: CrewAI playground web interface
Author-email: Lennex Zinyando <brizdigital@gmail.com>
Project-URL: Github, https://github.com/agentem-ai/crewai-playground
Project-URL: Bug Tracker, https://github.com/agentem-ai/crewai-playground/issues
Requires-Python: >=3.10
Requires-Dist: crewai>=0.148.0
Requires-Dist: click>=8.2.1
Requires-Dist: fastapi>=0.115.14
Requires-Dist: uvicorn>=0.35.0
Requires-Dist: pydantic>=2.11.7
Requires-Dist: opentelemetry-api>=1.34.1
Requires-Dist: opentelemetry-sdk>=1.34.1
Requires-Dist: opentelemetry-exporter-otlp>=1.34.1
Requires-Dist: opentelemetry-instrumentation
